{"aftereffects": [1, "/categories/aftereffects/", {"posts": [{"date": "01/11/2017", "isodate": "2017-01-11T22:46:32-05:00", "title": "Bear Cult and HOFSTADTERPILLAR", "url": "/posts/bear-cult-and-hofstadterpillar/"}]}], "animation": [1, "/categories/animation/", {"posts": [{"date": "01/11/2017", "isodate": "2017-01-11T22:46:32-05:00", "title": "Bear Cult and HOFSTADTERPILLAR", "url": "/posts/bear-cult-and-hofstadterpillar/"}]}], "audiovisual": [2, "/categories/audiovisual/", {"posts": [{"date": "01/11/2017", "isodate": "2017-01-11T22:05:57-05:00", "title": "ABSTRACT/CONCRETE", "url": "/posts/abstract-concrete/"}, {"date": "01/09/2017", "isodate": "2017-01-09T18:26:25-05:00", "title": "Data Sonification Using a Cortical Representation of Sound", "url": "/posts/cortical-sonification/"}]}], "autoencoder": [1, "/categories/autoencoder/", {"posts": [{"date": "01/09/2017", "isodate": "2017-01-09T18:26:25-05:00", "title": "Video Synthesis With Convolutional Autoencoders", "url": "/posts/convnet-video-feedback/"}]}], "bear cult": [1, "/categories/bear-cult/", {"posts": [{"date": "01/11/2017", "isodate": "2017-01-11T22:46:32-05:00", "title": "Bear Cult and HOFSTADTERPILLAR", "url": "/posts/bear-cult-and-hofstadterpillar/"}]}], "caffe": [1, "/categories/caffe/", {"posts": [{"date": "01/09/2017", "isodate": "2017-01-09T18:26:25-05:00", "title": "Video Synthesis With Convolutional Autoencoders", "url": "/posts/convnet-video-feedback/"}]}], "deep learning": [1, "/categories/deep-learning/", {"posts": [{"date": "01/09/2017", "isodate": "2017-01-09T18:26:25-05:00", "title": "Video Synthesis With Convolutional Autoencoders", "url": "/posts/convnet-video-feedback/"}]}], "douglas hofstadter": [1, "/categories/douglas-hofstadter/", {"posts": [{"date": "01/11/2017", "isodate": "2017-01-11T22:46:32-05:00", "title": "Bear Cult and HOFSTADTERPILLAR", "url": "/posts/bear-cult-and-hofstadterpillar/"}]}], "feedback": [5, "/categories/feedback/", {"posts": [{"date": "01/11/2017", "isodate": "2017-01-11T22:46:32-05:00", "title": "Bear Cult and HOFSTADTERPILLAR", "url": "/posts/bear-cult-and-hofstadterpillar/"}, {"date": "01/11/2017", "isodate": "2017-01-11T22:08:22-05:00", "title": "Video Feedback", "url": "/posts/video-feedback/"}, {"date": "01/11/2017", "isodate": "2017-01-11T22:05:57-05:00", "title": "ABSTRACT/CONCRETE", "url": "/posts/abstract-concrete/"}, {"date": "01/09/2017", "isodate": "2017-01-09T18:26:25-05:00", "title": "Making Music With No-input Mixer, SuperCollider, and Tidal", "url": "/posts/mixer-supercollider-tidal-music/"}, {"date": "01/09/2017", "isodate": "2017-01-09T18:26:25-05:00", "title": "Bendy: Wavetable Automata in Max", "url": "/posts/bendy/"}]}], "generative": [3, "/categories/generative/", {"posts": [{"date": "01/11/2017", "isodate": "2017-01-11T22:08:22-05:00", "title": "Video Feedback", "url": "/posts/video-feedback/"}, {"date": "01/11/2017", "isodate": "2017-01-11T22:05:57-05:00", "title": "ABSTRACT/CONCRETE", "url": "/posts/abstract-concrete/"}, {"date": "01/09/2017", "isodate": "2017-01-09T18:26:25-05:00", "title": "Bendy: Wavetable Automata in Max", "url": "/posts/bendy/"}]}], "hofstadterpillar": [1, "/categories/hofstadterpillar/", {"posts": [{"date": "01/11/2017", "isodate": "2017-01-11T22:46:32-05:00", "title": "Bear Cult and HOFSTADTERPILLAR", "url": "/posts/bear-cult-and-hofstadterpillar/"}]}], "jodie mack": [1, "/categories/jodie-mack/", {"posts": [{"date": "01/11/2017", "isodate": "2017-01-11T22:46:32-05:00", "title": "Bear Cult and HOFSTADTERPILLAR", "url": "/posts/bear-cult-and-hofstadterpillar/"}]}], "joseph campbell": [1, "/categories/joseph-campbell/", {"posts": [{"date": "01/11/2017", "isodate": "2017-01-11T22:46:32-05:00", "title": "Bear Cult and HOFSTADTERPILLAR", "url": "/posts/bear-cult-and-hofstadterpillar/"}]}], "lorenzo torresani": [1, "/categories/lorenzo-torresani/", {"posts": [{"date": "01/09/2017", "isodate": "2017-01-09T18:26:25-05:00", "title": "Video Synthesis With Convolutional Autoencoders", "url": "/posts/convnet-video-feedback/"}]}], "machine learning": [1, "/categories/machine-learning/", {"posts": [{"date": "01/09/2017", "isodate": "2017-01-09T18:26:25-05:00", "title": "Video Synthesis With Convolutional Autoencoders", "url": "/posts/convnet-video-feedback/"}]}], "matlab": [1, "/categories/matlab/", {"posts": [{"date": "01/09/2017", "isodate": "2017-01-09T18:26:25-05:00", "title": "Data Sonification Using a Cortical Representation of Sound", "url": "/posts/cortical-sonification/"}]}], "max": [3, "/categories/max/", {"posts": [{"date": "01/11/2017", "isodate": "2017-01-11T22:46:32-05:00", "title": "Bear Cult and HOFSTADTERPILLAR", "url": "/posts/bear-cult-and-hofstadterpillar/"}, {"date": "01/09/2017", "isodate": "2017-01-09T18:26:25-05:00", "title": "SIBA I|II|III", "url": "/posts/SIBA/"}, {"date": "01/09/2017", "isodate": "2017-01-09T18:26:25-05:00", "title": "Bendy: Wavetable Automata in Max", "url": "/posts/bendy/"}]}], "michael casey": [1, "/categories/michael-casey/", {"posts": [{"date": "01/09/2017", "isodate": "2017-01-09T18:26:25-05:00", "title": "Data Sonification Using a Cortical Representation of Sound", "url": "/posts/cortical-sonification/"}]}], "music": [1, "/categories/music/", {"posts": [{"date": "01/09/2017", "isodate": "2017-01-09T18:26:25-05:00", "title": "Making Music With No-input Mixer, SuperCollider, and Tidal", "url": "/posts/mixer-supercollider-tidal-music/"}]}], "neuroscience": [1, "/categories/neuroscience/", {"posts": [{"date": "01/09/2017", "isodate": "2017-01-09T18:26:25-05:00", "title": "Data Sonification Using a Cortical Representation of Sound", "url": "/posts/cortical-sonification/"}]}], "openFrameworks": [2, "/categories/openframeworks/", {"posts": [{"date": "01/11/2017", "isodate": "2017-01-11T22:05:57-05:00", "title": "ABSTRACT/CONCRETE", "url": "/posts/abstract-concrete/"}, {"date": "01/09/2017", "isodate": "2017-01-09T18:26:25-05:00", "title": "Video Synthesis With Convolutional Autoencoders", "url": "/posts/convnet-video-feedback/"}]}], "phasing": [1, "/categories/phasing/", {"posts": [{"date": "01/09/2017", "isodate": "2017-01-09T18:26:25-05:00", "title": "SIBA I|II|III", "url": "/posts/SIBA/"}]}], "recurrent": [1, "/categories/recurrent/", {"posts": [{"date": "01/09/2017", "isodate": "2017-01-09T18:26:25-05:00", "title": "Video Synthesis With Convolutional Autoencoders", "url": "/posts/convnet-video-feedback/"}]}], "shader": [1, "/categories/shader/", {"posts": [{"date": "01/11/2017", "isodate": "2017-01-11T22:08:22-05:00", "title": "Video Feedback", "url": "/posts/video-feedback/"}]}], "sonic": [6, "/categories/sonic/", {"posts": [{"date": "01/11/2017", "isodate": "2017-01-11T22:46:32-05:00", "title": "Bear Cult and HOFSTADTERPILLAR", "url": "/posts/bear-cult-and-hofstadterpillar/"}, {"date": "01/11/2017", "isodate": "2017-01-11T22:05:57-05:00", "title": "ABSTRACT/CONCRETE", "url": "/posts/abstract-concrete/"}, {"date": "01/09/2017", "isodate": "2017-01-09T18:26:25-05:00", "title": "SIBA I|II|III", "url": "/posts/SIBA/"}, {"date": "01/09/2017", "isodate": "2017-01-09T18:26:25-05:00", "title": "Making Music With No-input Mixer, SuperCollider, and Tidal", "url": "/posts/mixer-supercollider-tidal-music/"}, {"date": "01/09/2017", "isodate": "2017-01-09T18:26:25-05:00", "title": "Data Sonification Using a Cortical Representation of Sound", "url": "/posts/cortical-sonification/"}, {"date": "01/09/2017", "isodate": "2017-01-09T18:26:25-05:00", "title": "Bendy: Wavetable Automata in Max", "url": "/posts/bendy/"}]}], "sonification": [1, "/categories/sonification/", {"posts": [{"date": "01/09/2017", "isodate": "2017-01-09T18:26:25-05:00", "title": "Data Sonification Using a Cortical Representation of Sound", "url": "/posts/cortical-sonification/"}]}], "steve reich": [1, "/categories/steve-reich/", {"posts": [{"date": "01/09/2017", "isodate": "2017-01-09T18:26:25-05:00", "title": "SIBA I|II|III", "url": "/posts/SIBA/"}]}], "supercollider": [1, "/categories/supercollider/", {"posts": [{"date": "01/09/2017", "isodate": "2017-01-09T18:26:25-05:00", "title": "Making Music With No-input Mixer, SuperCollider, and Tidal", "url": "/posts/mixer-supercollider-tidal-music/"}]}], "tape music": [1, "/categories/tape-music/", {"posts": [{"date": "01/09/2017", "isodate": "2017-01-09T18:26:25-05:00", "title": "SIBA I|II|III", "url": "/posts/SIBA/"}]}], "tidal": [1, "/categories/tidal/", {"posts": [{"date": "01/09/2017", "isodate": "2017-01-09T18:26:25-05:00", "title": "Making Music With No-input Mixer, SuperCollider, and Tidal", "url": "/posts/mixer-supercollider-tidal-music/"}]}], "video": [1, "/categories/video/", {"posts": [{"date": "01/11/2017", "isodate": "2017-01-11T22:08:22-05:00", "title": "Video Feedback", "url": "/posts/video-feedback/"}]}], "video feedback": [1, "/categories/video-feedback/", {"posts": [{"date": "01/09/2017", "isodate": "2017-01-09T18:26:25-05:00", "title": "Video Synthesis With Convolutional Autoencoders", "url": "/posts/convnet-video-feedback/"}]}], "visual": [5, "/categories/visual/", {"posts": [{"date": "01/11/2017", "isodate": "2017-01-11T22:46:32-05:00", "title": "Bear Cult and HOFSTADTERPILLAR", "url": "/posts/bear-cult-and-hofstadterpillar/"}, {"date": "01/11/2017", "isodate": "2017-01-11T22:08:22-05:00", "title": "Video Feedback", "url": "/posts/video-feedback/"}, {"date": "01/11/2017", "isodate": "2017-01-11T22:05:57-05:00", "title": "ABSTRACT/CONCRETE", "url": "/posts/abstract-concrete/"}, {"date": "01/09/2017", "isodate": "2017-01-09T18:26:25-05:00", "title": "Data Sonification Using a Cortical Representation of Sound", "url": "/posts/cortical-sonification/"}, {"date": "01/09/2017", "isodate": "2017-01-09T18:26:25-05:00", "title": "Video Synthesis With Convolutional Autoencoders", "url": "/posts/convnet-video-feedback/"}]}]}